pyoidc_redis_session_backend/__init__.py
pyoidc_redis_session_backend-1.0.3.dist-info/LICENSE
pyoidc_redis_session_backend-1.0.3.dist-info/METADATA
pyoidc_redis_session_backend-1.0.3.dist-info/WHEEL
pyoidc_redis_session_backend-1.0.3.dist-info/top_level.txt
pyoidc_redis_session_backend-1.0.3.dist-info/RECORD
