Metadata-Version: 2.1
Name: pyoidc-redis-session-backend
Version: 1.0.3
Summary: Redis-based session storage for oic library
Home-page: https://github.com/alehuo/pyoidc-redis-session-backend
Author: alehuo
Author-email: aleksi.huotala@helsinki.fi
License: MIT
Platform: UNKNOWN
Classifier: Programming Language :: Python :: 3
Classifier: License :: OSI Approved :: MIT License
Classifier: Operating System :: OS Independent
Requires-Python: >=3.6
Requires-Dist: oic
Requires-Dist: jsonpickle
Requires-Dist: redis
Requires-Dist: pycryptodome
Requires-Dist: pycryptodomex
